{
  "kind": "BYF",
  "updated_at": "2026-07-17T02:39:29Z",
  "source": "tefas.gov.tr/api/funds/fonGetiriBazliBilgiGetir",
  "count": 31,
  "funds": [
    {
      "code": "BLH",
      "name": "AK PORTFÖY BIST LİKİT BANKA ENDEKSİ HİSSE SENEDİ YOĞUN BORSA YATIRIM FONU",
      "category": "Hisse Senedi Yoğun",
      "active": false,
      "risk": "7",
      "returns": {
        "1m": -11.2871,
        "3m": -8.4967,
        "6m": -3.8627,
        "1y": 3.9684,
        "ytd": -1.3216,
        "3y": null,
        "5y": null
      },
      "borsaTicker": "BLHRH"
    },
    {
      "code": "BND",
      "name": "AK PORTFÖY BIST BANKA DIŞI LİKİT 10 ENDEKSİ HİSSE SENEDİ YOĞUN BORSA YATIRIM FONU",
      "category": "Hisse Senedi Yoğun",
      "active": false,
      "risk": "7",
      "returns": {
        "1m": -0.9081,
        "3m": -2.8287,
        "6m": 18.0025,
        "1y": 49.1158,
        "ytd": 36.6986,
        "3y": null,
        "5y": null
      },
      "borsaTicker": "BNHTI"
    },
    {
      "code": "BOE",
      "name": "AK PORTFÖY BIST 30 ENDEKSİ HİSSE SENEDİ YOĞUN BORSA YATIRIM FONU",
      "category": "Hisse Senedi Yoğun",
      "active": false,
      "risk": "7",
      "returns": {
        "1m": -4,
        "3m": -3.9279,
        "6m": 12.4451,
        "1y": 36.1702,
        "ytd": 25.6545,
        "3y": null,
        "5y": null
      },
      "borsaTicker": "BORSA"
    },
    {
      "code": "BTL",
      "name": "OSMANLI PORTFÖY BIST TLREF ENDEKSİ (TL) BORSA YATIRIM FONU",
      "category": "Endeks Fon",
      "active": false,
      "risk": "2",
      "returns": {
        "1m": 3.2171,
        "3m": 10.0758,
        "6m": 20.3791,
        "1y": 46.9978,
        "ytd": 22.0665,
        "3y": null,
        "5y": null
      },
      "borsaTicker": "ISTC"
    },
    {
      "code": "DJA",
      "name": "QNB PORTFÖY QNB TEMİZ ENERJİ ENDEKSİ HİSSE SENEDİ YOĞUN BORSA YATIRIM FONU",
      "category": "Hisse Senedi Yoğun",
      "active": false,
      "risk": "7",
      "returns": {
        "1m": -4.463,
        "3m": -3.6026,
        "6m": 11.2736,
        "1y": 31.2764,
        "ytd": 18.5121,
        "3y": 51.9184,
        "5y": 683.7529
      },
      "borsaTicker": "DJIST"
    },
    {
      "code": "FGA",
      "name": "QNB PORTFÖY ALTIN KATILIM BORSA YATIRIM FONU",
      "category": "Altın Fonu",
      "active": false,
      "risk": "6",
      "returns": {
        "1m": -4.136,
        "3m": -11.4601,
        "6m": -4.6182,
        "1y": 42.0207,
        "ytd": -2.3408,
        "3y": 263.1616,
        "5y": 1076.9352
      },
      "borsaTicker": "FGOLD"
    },
    {
      "code": "FGS",
      "name": "QNB PORTFÖY GÜMÜŞ KATILIM BORSA YATIRIM FONU",
      "category": "Gümüş Fonu",
      "active": false,
      "risk": "7",
      "returns": {
        "1m": -16.4567,
        "3m": -22.8219,
        "6m": -29.4194,
        "1y": 75.8842,
        "ytd": -14.8969,
        "3y": 312.6745,
        "5y": 1052.7924
      },
      "borsaTicker": "FGOLDD"
    },
    {
      "code": "FUS",
      "name": "QNB PORTFÖY AMERİKAN DOLARI YABANCI BORSA YATIRIM FONU",
      "category": "Yabancı Fon",
      "active": false,
      "risk": "6",
      "returns": {
        "1m": 1.1803,
        "3m": 4.5683,
        "6m": 8.4594,
        "1y": 16.3694,
        "ytd": 8.8104,
        "3y": 77.1618,
        "5y": 433.496
      },
      "borsaTicker": "FSP500"
    },
    {
      "code": "ILK",
      "name": "İŞ PORTFÖY ALTIN KATILIM BORSA YATIRIM FONU",
      "category": "Altın Fonu",
      "active": false,
      "risk": "6",
      "returns": {
        "1m": -6.7686,
        "3m": -12.6789,
        "6m": -7.1739,
        "1y": 45.271,
        "ytd": -9.0199,
        "3y": null,
        "5y": null
      },
      "borsaTicker": "ILK22"
    },
    {
      "code": "KHO",
      "name": "AK PORTFÖY KATILIM 30 ENDEKSİ HİSSE SENEDİ YOĞUN BORSA YATIRIM FONU",
      "category": "Hisse Senedi Yoğun",
      "active": false,
      "risk": null,
      "returns": {
        "1m": null,
        "3m": null,
        "6m": null,
        "1y": null,
        "ytd": null,
        "3y": null,
        "5y": null
      },
      "borsaTicker": "KHOLD"
    },
    {
      "code": "LTK",
      "name": "AK PORTFÖY ALTIN KATILIM BORSA YATIRIM FONU",
      "category": "Altın Fonu",
      "active": false,
      "risk": "6",
      "returns": {
        "1m": -5.8091,
        "3m": -11.8637,
        "6m": null,
        "1y": null,
        "ytd": null,
        "3y": null,
        "5y": null
      },
      "borsaTicker": "LIKIT"
    },
    {
      "code": "MDL",
      "name": "AK PORTFÖY BIST 100 ENDEKSİ MODEL PORTFÖY  HİSSE SENEDİ YOĞUN BORSA YATIRIM FONU",
      "category": "Endeks Fon",
      "active": false,
      "risk": "7",
      "returns": {
        "1m": -7.0242,
        "3m": -6.5655,
        "6m": 1.1919,
        "1y": null,
        "ytd": 12.9876,
        "3y": null,
        "5y": null
      },
      "borsaTicker": "MDOLA"
    },
    {
      "code": "NBS",
      "name": "NUROL PORTFÖY BIST TLREF ENDEKSİ (TL) BORSA YATIRIM FONU",
      "category": "Endeks Fon",
      "active": false,
      "risk": "1",
      "returns": {
        "1m": 3.2684,
        "3m": 9.9242,
        "6m": 20.5553,
        "1y": null,
        "ytd": 22.256,
        "3y": null,
        "5y": null
      },
      "borsaTicker": "NNBSD"
    },
    {
      "code": "OHS",
      "name": "OSMANLI PORTFÖY KATILIM 30 ENDEKSİ HİSSE SENEDİ YOĞUN (TL) BORSA YATIRIM FONU",
      "category": "Hisse Senedi Yoğun",
      "active": false,
      "risk": "6",
      "returns": {
        "1m": -0.5839,
        "3m": 7.9539,
        "6m": 34.8938,
        "1y": 70.6606,
        "ytd": 50.8052,
        "3y": null,
        "5y": null
      },
      "borsaTicker": "OYAKS"
    },
    {
      "code": "OHY",
      "name": "OSMANLI PORTFÖY BİST 30 ENDEKSİ HİSSE SENEDİ YOĞUN BORSA YATIRIM FONU",
      "category": "Hisse Senedi Yoğun",
      "active": false,
      "risk": "6",
      "returns": {
        "1m": -3.9889,
        "3m": -3.7657,
        "6m": 13.6426,
        "1y": 35.5155,
        "ytd": 25.5687,
        "3y": null,
        "5y": null
      },
      "borsaTicker": "OYAKP"
    },
    {
      "code": "OPE",
      "name": "OSMANLI PORTFÖY BIST TEMETTÜ 25 ENDEKSİ HİSSE SENEDİ YOĞUN (TL) BORSA YATIRIM FONU",
      "category": "Hisse Senedi Yoğun",
      "active": false,
      "risk": "6",
      "returns": {
        "1m": -3.4006,
        "3m": -1.7857,
        "6m": 9.3023,
        "1y": 28.2242,
        "ytd": 19.3995,
        "3y": null,
        "5y": null
      },
      "borsaTicker": "OYUME"
    },
    {
      "code": "OPK",
      "name": "OSMANLI PORTFÖY KAR PAYI ÖDEYEN BIST GYO ENDEKSİ HİSSE SENEDİ YOĞUN (TL) BORSA YATIRIM FONU",
      "category": "Hisse Senedi Yoğun",
      "active": false,
      "risk": "7",
      "returns": {
        "1m": -5.9794,
        "3m": -5.1412,
        "6m": 2.5377,
        "1y": 23.1007,
        "ytd": 11.8822,
        "3y": null,
        "5y": null
      },
      "borsaTicker": "OYAGB"
    },
    {
      "code": "ZBB",
      "name": "ZİRAAT PORTFÖY BIST 30 ENDEKSİ HİSSE SENEDİ YOĞUN BORSA YATIRIM FONU",
      "category": "Hisse Senedi Yoğun",
      "active": false,
      "risk": "7",
      "returns": {
        "1m": -3.9229,
        "3m": -4.1898,
        "6m": 12.534,
        "1y": 35.3057,
        "ytd": 25.6527,
        "3y": 130.8164,
        "5y": 1082.5714
      },
      "borsaTicker": "ZPBDL"
    },
    {
      "code": "ZBP",
      "name": "ZİRAAT PORTFÖY BIST LİKİT BANKA ENDEKSİ HİSSE SENEDİ YOĞUN BORSA YATIRIM FONU",
      "category": "Hisse Senedi Yoğun",
      "active": false,
      "risk": "7",
      "returns": {
        "1m": -11.2791,
        "3m": -8.579,
        "6m": -3.3443,
        "1y": 4.235,
        "ytd": -1.2681,
        "3y": 186.6697,
        "5y": 1480.3645
      },
      "borsaTicker": "ZSILV"
    },
    {
      "code": "ZEA",
      "name": "ZİRAAT PORTFÖY BIST 30 EŞİT AĞIRLIKLI ENDEKSİ HİSSE SENEDİ YOĞUN BORSA YATIRIM FONU",
      "category": "Hisse Senedi Yoğun",
      "active": false,
      "risk": "7",
      "returns": {
        "1m": -3.9941,
        "3m": -1.6418,
        "6m": 19.8523,
        "1y": 39.9712,
        "ytd": 31.643,
        "3y": 106.644,
        "5y": 991.3677
      },
      "borsaTicker": "ZPLIB"
    },
    {
      "code": "ZEO",
      "name": "ZİRAAT PORTFÖY BIST 50-30 ENDEKSİ HİSSE SENEDİ YOĞUN BORSA YATIRIM FONU",
      "category": "Hisse Senedi Yoğun",
      "active": false,
      "risk": "6",
      "returns": {
        "1m": -5.8418,
        "3m": -7.5667,
        "6m": -2.1501,
        "1y": 20.584,
        "ytd": 6.0302,
        "3y": 63.2208,
        "5y": 698.1431
      },
      "borsaTicker": "ZPX30"
    },
    {
      "code": "ZGD",
      "name": "ZİRAAT PORTFÖY ALTIN KATILIM  BORSA YATIRIM FONU",
      "category": "Altın Fonu",
      "active": false,
      "risk": "6",
      "returns": {
        "1m": -6.2681,
        "3m": -12.3645,
        "6m": -4.043,
        "1y": 46.5224,
        "ytd": -7.4087,
        "3y": 271.1621,
        "5y": 1189.374
      },
      "borsaTicker": "ZGOLD"
    },
    {
      "code": "ZKE",
      "name": "ZİRAAT PORTFÖY BIST KATILIM 30 EŞİT AĞIRLIKLI ENDEKSİ HİSSE SENEDİ YOĞUN BORSA YATIRIM FONU",
      "category": "Hisse Senedi Yoğun",
      "active": false,
      "risk": "6",
      "returns": {
        "1m": -4.6347,
        "3m": 5.045,
        "6m": 34.1772,
        "1y": 68.4971,
        "ytd": 43.1846,
        "3y": 136.8635,
        "5y": 846.941
      },
      "borsaTicker": "ZHYS"
    },
    {
      "code": "ZKP",
      "name": "ZİRAAT PORTFÖY BIST KATILIM 30 ENDEKSİ HİSSE SENEDİ YOĞUN BORSA YATIRIM FONU",
      "category": "Hisse Senedi Yoğun",
      "active": false,
      "risk": "6",
      "returns": {
        "1m": -0.9615,
        "3m": 4.3778,
        "6m": 28.9757,
        "1y": 67.2078,
        "ytd": 39.1892,
        "3y": 164.591,
        "5y": 1258.8391
      },
      "borsaTicker": "ZPLAT"
    },
    {
      "code": "ZPP",
      "name": "ZİRAAT PORTFÖY BIST BANKA DIŞI LİKİT 10 ENDEKSİ HİSSE SENEDİ YOĞUN BORSA YATIRIM FONU",
      "category": "Hisse Senedi Yoğun",
      "active": false,
      "risk": "7",
      "returns": {
        "1m": 0.9156,
        "3m": -1.2081,
        "6m": 20.4848,
        "1y": 52.6189,
        "ytd": 39.3623,
        "3y": 135.7043,
        "5y": 1218.2527
      },
      "borsaTicker": "ZPLUS"
    },
    {
      "code": "ZPT",
      "name": "ZİRAAT PORTFÖY YILDIZ PAZAR TEKNOLOJİ VE İLETİŞİM 10 ENDEKSİ HİSSE SENEDİ YOĞUN BORSA YATIRIM FONU",
      "category": "Hisse Senedi Yoğun",
      "active": false,
      "risk": "7",
      "returns": {
        "1m": -3.7138,
        "3m": 8.1212,
        "6m": 37.3216,
        "1y": 53.8606,
        "ytd": 50.8082,
        "3y": 198.9803,
        "5y": 738.8965
      },
      "borsaTicker": "ZPETR"
    },
    {
      "code": "ZRE",
      "name": "ZİRAAT PORTFÖY RİSK EŞİT BANKA DIŞI 20 ENDEKSİ HİSSE SENEDİ YOĞUN BORSA YATIRIM FONU",
      "category": "Hisse Senedi Yoğun",
      "active": false,
      "risk": "6",
      "returns": {
        "1m": -0.3826,
        "3m": 1.0255,
        "6m": 26.5186,
        "1y": 48.3516,
        "ytd": 41.4435,
        "3y": 97.9257,
        "5y": 931.4092
      },
      "borsaTicker": "ZGYO"
    },
    {
      "code": "ZSR",
      "name": "ZİRAAT PORTFÖY BIST SÜRDÜRÜLEBİLİRLİK 25 ENDEKSİ HİSSE SENEDİ YOĞUN BORSA YATIRIM FONU",
      "category": "Hisse Senedi Yoğun",
      "active": false,
      "risk": "6",
      "returns": {
        "1m": -4.8805,
        "3m": -6.6203,
        "6m": 6.7743,
        "1y": 26.7404,
        "ytd": 19.2132,
        "3y": 131.6075,
        "5y": null
      },
      "borsaTicker": "ZSRDQ"
    },
    {
      "code": "ZTK",
      "name": "ZİRAAT PORTFÖY BIST TLREFK ENDEKSİ KATILIM (TL) BORSA YATIRIM FONU",
      "category": "Endeks Fon",
      "active": false,
      "risk": "2",
      "returns": {
        "1m": 3.3006,
        "3m": 10.2306,
        "6m": 20.7625,
        "1y": null,
        "ytd": 22.4499,
        "3y": null,
        "5y": null
      },
      "borsaTicker": "ZTKYE"
    },
    {
      "code": "ZTM",
      "name": "ZİRAAT PORTFÖY BIST TEMETTÜ 25 ENDEKSİ HİSSE SENEDİ YOĞUN BORSA YATIRIM FONU",
      "category": "Hisse Senedi Yoğun",
      "active": false,
      "risk": "6",
      "returns": {
        "1m": -3.6815,
        "3m": -1.2845,
        "6m": 11.5513,
        "1y": 32.4121,
        "ytd": 22.8847,
        "3y": 148.6519,
        "5y": 977.3949
      },
      "borsaTicker": "ZTUR"
    },
    {
      "code": "ZTR",
      "name": "ZİRAAT PORTFÖY BIST TLREF ENDEKSİ (TL) BORSA YATIRIM FONU",
      "category": "Endeks Fon",
      "active": false,
      "risk": "2",
      "returns": {
        "1m": 3.2575,
        "3m": 10.2682,
        "6m": 20.8544,
        "1y": null,
        "ytd": 22.5431,
        "3y": null,
        "5y": null
      },
      "borsaTicker": "ZTURK"
    }
  ]
}
